nbwatch/__init__.py
nbwatch/templates/index.html
nbwatch-0.2.2.dist-info/entry_points.txt
nbwatch-0.2.2.dist-info/LICENSE
nbwatch-0.2.2.dist-info/WHEEL
nbwatch-0.2.2.dist-info/METADATA
nbwatch-0.2.2.dist-info/RECORD
