Metadata-Version: 2.1
Name: nbwatch
Version: 0.2.2
Summary: Preview IPython notebooks in your browser.
License: MIT
Author: Jeremiah Boby
Author-email: mail@jeremiahboby.me
Requires-Python: >=3.8,<4.0
Classifier: License :: OSI Approved :: MIT License
Classifier: Programming Language :: Python :: 3
Requires-Dist: docopt (>=0.6.2,<0.7.0)
Requires-Dist: flask (>=1.1.1,<2.0.0)
Requires-Dist: ipykernel (>=5.1.3,<6.0.0)
Requires-Dist: jupyter_client (>=5.3.4,<6.0.0)
Requires-Dist: nbconvert (>=5.6.1,<6.0.0)
